setup.py
drtb/__init__.py
drtb/drtb.py
drtb.egg-info/PKG-INFO
drtb.egg-info/SOURCES.txt
drtb.egg-info/dependency_links.txt
drtb.egg-info/top_level.txt