Metadata-Version: 2.1
Name: drtb
Version: 1.0
Summary: used for drtb cmd
Author: DaRealTrueBlue
Author-email: ethan.lane021207@gmail.com
